{"type": "xviz/state_update", "data": {"update_type": "snapshot", "updates": [{"timestamp": 1014.2, "poses": {"/vehicle_pose": {"timestamp": 1014.2, "map_origin": {"longitude": 0, "latitude": 0, "altitude": 0}, "orientation": [0, 0, 0]}}, "primitives": {"/object/shape": {"polygons": [{"vertices": [[9.54, 4.38, 0], [13.85, 4.38, 0], [13.84, 2.7, 0], [9.53, 2.7, 0]], "base": {"object_id": "object-1", "style": {"fill_color": "#fb0", "height": 1.66}}}, {"vertices": [[22.78, 4.7, 0], [27.09, 4.7, 0], [27.08, 3.02, 0], [22.77, 3.02, 0]], "base": {"object_id": "object-1", "style": {"fill_color": "#555", "height": 1.66}}}, {"vertices": [[9.96, 8.07, 0], [14.27, 8.07, 0], [14.26, 6.39, 0], [9.95, 6.39, 0]], "base": {"object_id": "object-1", "style": {"fill_color": "#fb0", "height": 1.66}}}, {"vertices": [[41.94, -2.95, 0], [46.25, -2.95, 0], [46.24, -4.63, 0], [41.93, -4.63, 0]], "base": {"object_id": "object-1", "style": {"fill_color": "#555", "height": 1.66}}}, {"vertices": [[36.26, 5.44, 0], [40.57, 5.44, 0], [40.56, 3.76, 0], [36.25, 3.76, 0]], "base": {"object_id": "object-1", "style": {"fill_color": "#555", "height": 1.66}}}, {"vertices": [[50.61, 5.76, 0], [54.92, 5.76, 0], [54.91, 4.08, 0], [50.6, 4.08, 0]], "base": {"object_id": "object-1", "style": {"fill_color": "#555", "height": 1.66}}}, {"vertices": [[36.74, -0.22, 0], [41.05, -0.22, 0], [41.04, -1.9, 0], [36.73, -1.9, 0]], "base": {"object_id": "object-1", "style": {"fill_color": "#555", "height": 1.66}}}, {"vertices": [[29.77, 8.81, 0], [34.08, 8.81, 0], [34.07, 7.13, 0], [29.76, 7.13, 0]], "base": {"object_id": "object-1", "style": {"fill_color": "#555", "height": 1.66}}}, {"vertices": [[12.63, 8.71, 0], [16.94, 8.71, 0], [16.93, 7.03, 0], [12.62, 7.03, 0]], "base": {"object_id": "object-1", "style": {"fill_color": "#fb0", "height": 1.66}}}]}, "/object/label": {"texts": [{"position": [11.69, 3.54, 1.8599999999999999], "text": "'car': 11 m"}, {"position": [24.93, 3.86, 1.8599999999999999], "text": "'car': 24 m"}, {"position": [12.11, 7.23, 1.8599999999999999], "text": "'car': 12 m"}, {"position": [44.09, -3.79, 1.8599999999999999], "text": "'car': 44 m"}, {"position": [38.41, 4.6, 1.8599999999999999], "text": "'car': 38 m"}, {"position": [52.76, 4.92, 1.8599999999999999], "text": "'car': 52 m"}, {"position": [38.89, -1.06, 1.8599999999999999], "text": "'car': 38 m"}, {"position": [31.92, 7.97, 1.8599999999999999], "text": "'car': 31 m"}, {"position": [14.78, 7.87, 1.8599999999999999], "text": "'car': 14 m"}]}, "/prediction/trajectory": {"polylines": []}}}]}}