{"type": "xviz/state_update", "data": {"update_type": "snapshot", "updates": [{"timestamp": 1019.9, "poses": {"/vehicle_pose": {"timestamp": 1019.9, "map_origin": {"longitude": 0, "latitude": 0, "altitude": 0}, "orientation": [0, 0, 0]}}, "primitives": {"/object/shape": {"polygons": [{"vertices": [[28.03, 3.35, 0], [32.34, 3.35, 0], [32.33, 1.67, 0], [28.02, 1.67, 0]], "base": {"object_id": "object-1", "style": {"fill_color": "#555", "height": 1.66}}}, {"vertices": [[8.92, 7.43, 0], [13.23, 7.43, 0], [13.22, 5.75, 0], [8.91, 5.75, 0]], "base": {"object_id": "object-1", "style": {"fill_color": "#fb0", "height": 1.66}}}, {"vertices": [[14.42, 4.38, 0], [18.73, 4.38, 0], [18.72, 2.7, 0], [14.41, 2.7, 0]], "base": {"object_id": "object-1", "style": {"fill_color": "#fb0", "height": 1.66}}}, {"vertices": [[18.01, 8.39, 0], [22.32, 8.39, 0], [22.31, 6.71, 0], [18.0, 6.71, 0]], "base": {"object_id": "object-1", "style": {"fill_color": "#555", "height": 1.66}}}, {"vertices": [[26.95, 10.74, 0], [31.26, 10.74, 0], [31.25, 9.06, 0], [26.94, 9.06, 0]], "base": {"object_id": "object-1", "style": {"fill_color": "#555", "height": 1.66}}}, {"vertices": [[41.26, 7.85, 0], [45.57, 7.85, 0], [45.56, 6.17, 0], [41.25, 6.17, 0]], "base": {"object_id": "object-1", "style": {"fill_color": "#555", "height": 1.66}}}]}, "/object/label": {"texts": [{"position": [30.18, 2.51, 1.8599999999999999], "text": "'car': 30 m"}, {"position": [11.07, 6.59, 1.8599999999999999], "text": "'car': 11 m"}, {"position": [16.57, 3.54, 1.8599999999999999], "text": "'car': 16 m"}, {"position": [20.16, 7.55, 1.8599999999999999], "text": "'car': 20 m"}, {"position": [29.1, 9.9, 1.8599999999999999], "text": "'car': 29 m"}, {"position": [43.41, 7.01, 1.8599999999999999], "text": "'car': 43 m"}]}, "/prediction/trajectory": {"polylines": []}}}]}}