{"type": "xviz/state_update", "data": {"update_type": "snapshot", "updates": [{"timestamp": 1004.4, "poses": {"/vehicle_pose": {"timestamp": 1004.4, "map_origin": {"longitude": 0, "latitude": 0, "altitude": 0}, "orientation": [0, 0, 0]}}, "primitives": {"/object/shape": {"polygons": [{"vertices": [[7.75, 4.05, 0], [12.06, 4.05, 0], [12.05, 2.37, 0], [7.74, 2.37, 0]], "base": {"object_id": "object-1", "style": {"fill_color": "#f00", "height": 1.66}}}, {"vertices": [[9.71, 7.59, 0], [14.02, 7.59, 0], [14.01, 5.91, 0], [9.7, 5.91, 0]], "base": {"object_id": "object-1", "style": {"fill_color": "#fb0", "height": 1.66}}}, {"vertices": [[13.53, -1.89, 0], [17.84, -1.89, 0], [17.83, -3.57, 0], [13.52, -3.57, 0]], "base": {"object_id": "object-1", "style": {"fill_color": "#fb0", "height": 1.66}}}, {"vertices": [[32.4, -2.47, 0], [36.71, -2.47, 0], [36.7, -4.15, 0], [32.39, -4.15, 0]], "base": {"object_id": "object-1", "style": {"fill_color": "#555", "height": 1.66}}}, {"vertices": [[17.52, 4.05, 0], [21.83, 4.05, 0], [21.82, 2.37, 0], [17.51, 2.37, 0]], "base": {"object_id": "object-1", "style": {"fill_color": "#fb0", "height": 1.66}}}, {"vertices": [[58.74, 2.22, 0], [63.05, 2.22, 0], [63.04, 0.54, 0], [58.73, 0.54, 0]], "base": {"object_id": "object-1", "style": {"fill_color": "#555", "height": 1.66}}}, {"vertices": [[19.33, 7.43, 0], [23.64, 7.43, 0], [23.63, 5.75, 0], [19.32, 5.75, 0]], "base": {"object_id": "object-1", "style": {"fill_color": "#555", "height": 1.66}}}, {"vertices": [[27.97, 4.79, 0], [32.28, 4.79, 0], [32.27, 3.11, 0], [27.96, 3.11, 0]], "base": {"object_id": "object-1", "style": {"fill_color": "#555", "height": 1.66}}}, {"vertices": [[56.29, 4.95, 0], [60.6, 4.95, 0], [60.59, 3.27, 0], [56.28, 3.27, 0]], "base": {"object_id": "object-1", "style": {"fill_color": "#555", "height": 1.66}}}, {"vertices": [[59.24, -1.51, 0], [63.55, -1.51, 0], [63.54, -3.19, 0], [59.23, -3.19, 0]], "base": {"object_id": "object-1", "style": {"fill_color": "#555", "height": 1.66}}}, {"vertices": [[14.4, 19.64, 0], [18.71, 19.64, 0], [18.7, 17.96, 0], [14.39, 17.96, 0]], "base": {"object_id": "object-1", "style": {"fill_color": "#fb0", "height": 1.66}}}]}, "/object/label": {"texts": [{"position": [9.9, 3.21, 1.8599999999999999], "text": "'car': 9 m"}, {"position": [11.86, 6.75, 1.8599999999999999], "text": "'car': 11 m"}, {"position": [15.68, -2.73, 1.8599999999999999], "text": "'car': 15 m"}, {"position": [34.55, -3.31, 1.8599999999999999], "text": "'car': 34 m"}, {"position": [19.67, 3.21, 1.8599999999999999], "text": "'car': 19 m"}, {"position": [60.89, 1.38, 1.8599999999999999], "text": "'car': 60 m"}, {"position": [21.48, 6.59, 1.8599999999999999], "text": "'car': 21 m"}, {"position": [30.12, 3.95, 1.8599999999999999], "text": "'car': 30 m"}, {"position": [58.44, 4.11, 1.8599999999999999], "text": "'car': 58 m"}, {"position": [61.39, -2.35, 1.8599999999999999], "text": "'car': 61 m"}, {"position": [16.55, 18.8, 1.8599999999999999], "text": "'car': 16 m"}]}, "/prediction/trajectory": {"polylines": []}}}]}}