{"type": "xviz/state_update", "data": {"update_type": "snapshot", "updates": [{"timestamp": 1048.3, "poses": {"/vehicle_pose": {"timestamp": 1048.3, "map_origin": {"longitude": 0, "latitude": 0, "altitude": 0}, "orientation": [0, 0, 0]}}, "primitives": {"/object/shape": {"polygons": [{"vertices": [[4.08, 4.54, 0], [8.39, 4.54, 0], [8.38, 2.86, 0], [4.07, 2.86, 0]], "base": {"object_id": "object-1", "style": {"fill_color": "#f00", "height": 1.66}}}, {"vertices": [[11.09, 5.5, 0], [15.4, 5.5, 0], [15.39, 3.82, 0], [11.08, 3.82, 0]], "base": {"object_id": "object-1", "style": {"fill_color": "#fb0", "height": 1.66}}}, {"vertices": [[37.02, 2.38, 0], [41.33, 2.38, 0], [41.32, 0.7, 0], [37.01, 0.7, 0]], "base": {"object_id": "object-1", "style": {"fill_color": "#555", "height": 1.66}}}, {"vertices": [[12.82, 11.28, 0], [17.13, 11.28, 0], [17.12, 9.6, 0], [12.81, 9.6, 0]], "base": {"object_id": "object-1", "style": {"fill_color": "#fb0", "height": 1.66}}}, {"vertices": [[7.0, 10.8, 0], [11.31, 10.8, 0], [11.3, 9.12, 0], [6.99, 9.12, 0]], "base": {"object_id": "object-1", "style": {"fill_color": "#f00", "height": 1.66}}}, {"vertices": [[46.5, 6.08, 0], [50.81, 6.08, 0], [50.8, 4.4, 0], [46.49, 4.4, 0]], "base": {"object_id": "object-1", "style": {"fill_color": "#555", "height": 1.66}}}, {"vertices": [[18.1, 7.27, 0], [22.41, 7.27, 0], [22.4, 5.59, 0], [18.09, 5.59, 0]], "base": {"object_id": "object-1", "style": {"fill_color": "#555", "height": 1.66}}}, {"vertices": [[27.89, 5.6, 0], [32.2, 5.6, 0], [32.19, 3.92, 0], [27.88, 3.92, 0]], "base": {"object_id": "object-1", "style": {"fill_color": "#555", "height": 1.66}}}]}, "/object/label": {"texts": [{"position": [6.23, 3.7, 1.8599999999999999], "text": "'car': 6 m"}, {"position": [13.24, 4.66, 1.8599999999999999], "text": "'car': 13 m"}, {"position": [39.17, 1.54, 1.8599999999999999], "text": "'car': 39 m"}, {"position": [14.97, 10.44, 1.8599999999999999], "text": "'car': 14 m"}, {"position": [9.15, 9.96, 1.8599999999999999], "text": "'car': 9 m"}, {"position": [48.65, 5.24, 1.8599999999999999], "text": "'car': 48 m"}, {"position": [20.25, 6.43, 1.8599999999999999], "text": "'car': 20 m"}, {"position": [30.04, 4.76, 1.8599999999999999], "text": "'car': 30 m"}]}, "/prediction/trajectory": {"polylines": []}}}]}}