{"type": "xviz/state_update", "data": {"update_type": "snapshot", "updates": [{"timestamp": 1062.8, "poses": {"/vehicle_pose": {"timestamp": 1062.8, "map_origin": {"longitude": 0, "latitude": 0, "altitude": 0}, "orientation": [0, 0, 0]}}, "primitives": {"/object/shape": {"polygons": [{"vertices": [[30.59, -5.52, 0], [34.9, -5.52, 0], [34.89, -7.2, 0], [30.58, -7.2, 0]], "base": {"object_id": "object-1", "style": {"fill_color": "#555", "height": 1.66}}}, {"vertices": [[50.82, -13.08, 0], [55.13, -13.08, 0], [55.12, -14.76, 0], [50.81, -14.76, 0]], "base": {"object_id": "object-1", "style": {"fill_color": "#555", "height": 1.66}}}, {"vertices": [[16.86, 12.41, 0], [21.17, 12.41, 0], [21.16, 10.73, 0], [16.85, 10.73, 0]], "base": {"object_id": "object-1", "style": {"fill_color": "#fb0", "height": 1.66}}}, {"vertices": [[50.37, -25.93, 0], [54.68, -25.93, 0], [54.67, -27.61, 0], [50.36, -27.61, 0]], "base": {"object_id": "object-1", "style": {"fill_color": "#555", "height": 1.66}}}, {"vertices": [[10.37, 12.25, 0], [14.68, 12.25, 0], [14.67, 10.57, 0], [10.36, 10.57, 0]], "base": {"object_id": "object-1", "style": {"fill_color": "#fb0", "height": 1.66}}}]}, "/object/label": {"texts": [{"position": [32.739999999999995, -6.36, 1.8599999999999999], "text": "'car': 32 m"}, {"position": [52.97, -13.92, 1.8599999999999999], "text": "'car': 52 m"}, {"position": [19.01, 11.57, 1.8599999999999999], "text": "'car': 19 m"}, {"position": [52.52, -26.77, 1.8599999999999999], "text": "'car': 52 m"}, {"position": [12.52, 11.41, 1.8599999999999999], "text": "'car': 12 m"}]}, "/prediction/trajectory": {"polylines": []}}}]}}